nure/__init__.py
nure/archive.py
nure/array.py
nure/dataframe.py
nure/datetime.py
nure/debug.py
nure/dict.py
nure/func.py
nure/meta.py
nure/path.py
nure/volatitle.py
nure/code/__init__.py
nure/code/label_coder.py
nure/image/__init__.py
nure/image/annotate.py
nure/image/func.py
nure/image/pil.py
nure/sync/__init__.py
nure/sync/bigquery.py
nure/sync/cache.py
nure/sync/googlesheet.py
nure/sync/postgre.py
nure/sync/s3.py
nure/sync/sql.py
nure/sync/suffix.py
nure-2025.11.17.dist-info/licenses/LICENSE
venv/bin/jp.py
venv/bin/rst2html.py
venv/bin/rst2html4.py
venv/bin/rst2html5.py
venv/bin/rst2latex.py
venv/bin/rst2man.py
venv/bin/rst2odt.py
venv/bin/rst2odt_prepstyles.py
venv/bin/rst2pseudoxml.py
venv/bin/rst2s5.py
venv/bin/rst2xetex.py
venv/bin/rst2xml.py
venv/bin/rstpep2html.py
nure-2025.11.17.dist-info/METADATA
nure-2025.11.17.dist-info/WHEEL
nure-2025.11.17.dist-info/top_level.txt
nure-2025.11.17.dist-info/RECORD
