Metadata-Version: 2.4
Name: nure
Version: 2025.11.17
Summary: Data Science Utilities
Author-email: Trung Tran <tranduytrung@outlook.com>
License-Expression: GPL-3.0-or-later
Project-URL: Homepage, https://github.com/tranduytrung/nure
Project-URL: Issues, https://github.com/tranduytrung/nure/issues
Classifier: Programming Language :: Python :: 3
Classifier: Operating System :: OS Independent
Requires-Python: >=3.8
License-File: LICENSE
Requires-Dist: more-itertools
Requires-Dist: numpy
Requires-Dist: pandas
Requires-Dist: pyarrow
Provides-Extra: image
Requires-Dist: pillow; extra == "image"
Requires-Dist: opencv-python-headless; extra == "image"
Provides-Extra: sql
Requires-Dist: mysql-connector-python; extra == "sql"
Requires-Dist: sqlalchemy-bigquery; extra == "sql"
Requires-Dist: psycopg2-binary; extra == "sql"
Provides-Extra: aws
Requires-Dist: boto3; extra == "aws"
Dynamic: license-file
